{
  "copyright": [
    "Copyright (C) 2019-2021 Swift Navigation Inc.",
    "Contact: https://support.swiftnav.com",
    "",
    "This source is subject to the license found in the file 'LICENSE' which must",
    "be be distributed together with this source. All other rights reserved.",
    "",
    "THIS CODE AND INFORMATION IS PROVIDED 'AS IS' WITHOUT WARRANTY OF ANY KIND,",
    "EITHER EXPRESSED OR IMPLIED, INCLUDING BUT NOT LIMITED TO THE IMPLIED",
    "WARRANTIES OF MERCHANTABILITY AND/OR FITNESS FOR A PARTICULAR PURPOSE."
  ],
  "$schema": "http://json-schema.org/draft-06/schema#",
  "$id": "#SubSystemReport",
  "title":"SubSystemReport",
  "description":"Report the general and specific state of a sub-system.  If the generic state is reported as initializing, the specific state should be ignored.\n",
  "type": "object",
  "properties": {
    "component": {"type": "integer"},
    "generic": {"type": "integer"},
    "specific": {"type": "integer"}
  },
  "required": [
    "component",
    "generic",
    "specific"
  ]
}